cyberbot/__init__.py
cyberbot/core.py
cyberbot/rep.py
cyberbot-1.1.6.dist-info/licenses/LICENSE
cyberbot-1.1.6.dist-info/METADATA
cyberbot-1.1.6.dist-info/WHEEL
cyberbot-1.1.6.dist-info/top_level.txt
cyberbot-1.1.6.dist-info/RECORD
