Metadata-Version: 2.4
Name: cyberbot
Version: 1.1.6
Summary: CyberBot is a versatile AI-powered automation bot and SDK designed for developers and tech enthusiasts. It simplifies bot creation, automates repetitive tasks, and enables seamless API integration. With support for Python and JavaScript, CyberBot helps you manage workflows, monitor activity, and interact with servers effortlessly—all while keeping security and scalability in mind.
Author: Alex Austin
Author-email: benmap40@gmail.com
License: MIT
Classifier: Programming Language :: Python :: 3
Classifier: Operating System :: OS Independent
Classifier: Topic :: Security
Classifier: Framework :: Flask
Requires-Python: >=3.7
License-File: LICENSE
Requires-Dist: Flask
Requires-Dist: pycryptodome
Requires-Dist: cryptography
Dynamic: author
Dynamic: author-email
Dynamic: classifier
Dynamic: license
Dynamic: license-file
Dynamic: requires-dist
Dynamic: requires-python
Dynamic: summary
